topsis_package/__init__.py
topsis_package/main.py
topsis_102203409-1.0.dist-info/METADATA
topsis_102203409-1.0.dist-info/WHEEL
topsis_102203409-1.0.dist-info/entry_points.txt
topsis_102203409-1.0.dist-info/top_level.txt
topsis_102203409-1.0.dist-info/RECORD
