Metadata-Version: 2.1
Name: topsis-102203409
Version: 1.0
Summary: A Python package for implementing TOPSIS (Technique for Order of Preference by Similarity to Ideal Solution).
Home-page: https://github.com/AGtheOG/TopsisPackagePypi
Author: Arin Goyal
Author-email: aringoyal15@gmail.com
License: UNKNOWN
Platform: UNKNOWN
Classifier: Programming Language :: Python :: 3
Classifier: Operating System :: OS Independent
Requires-Python: >=3.6
Requires-Dist: pandas>=1.0.0
Requires-Dist: numpy>=1.19.0
